fleetglue_client/__init__.py
fleetglue_client/account.py
fleetglue_client/alert.py
fleetglue_client/api_handler.py
fleetglue_client/cli/__init__.py
fleetglue_client/cli/commands/__init__.py
fleetglue_client/cli/commands/base.py
fleetglue_client/cli/commands/device.py
fleetglue_client/cli/commands/setup.py
fleetglue_client/cli/fleetglue.py
fleetglue_client/credentials.py
fleetglue_client/device.py
fleetglue_client/entity.py
fleetglue_client/helpers.py
fleetglue_client/op_deployment.py
fleetglue_client/op_deployment_service.py
fleetglue_client/token.py
fleetglue_client/tools/__init__.py
fleetglue_client/tools/buffering_tracer.py
fleetglue_client/tools/monitoring.py
fleetglue_client/user.py
fleetglue_client/zone.py
fleetglue_client-2.0.2.dist-info/METADATA
fleetglue_client-2.0.2.dist-info/WHEEL
fleetglue_client-2.0.2.dist-info/entry_points.txt
fleetglue_client-2.0.2.dist-info/RECORD
