Metadata-Version: 2.1
Name: fleetglue-client
Version: 2.0.2
Summary: Python client for FleetGlue API
Author: Pablo Díaz Ogni
Author-email: pablo@fleetglue.com
Requires-Python: >=3.8,<4.0
Classifier: Programming Language :: Python :: 3
Classifier: Programming Language :: Python :: 3.8
Classifier: Programming Language :: Python :: 3.9
Classifier: Programming Language :: Python :: 3.10
Classifier: Programming Language :: Python :: 3.11
Classifier: Programming Language :: Python :: 3.12
Requires-Dist: requests (>=2.28.1,<3.0.0)
